{"start": {"connected": [{"socket": 8, "local_host": "148.88.224.174", "local_port": 58766, "remote_host": "164.132.43.137", "remote_port": 5201}, {"socket": 10, "local_host": "148.88.224.174", "local_port": 58768, "remote_host": "164.132.43.137", "remote_port": 5201}, {"socket": 12, "local_host": "148.88.224.174", "local_port": 58770, "remote_host": "164.132.43.137", "remote_port": 5201}, {"socket": 14, "local_host": "148.88.224.174", "local_port": 58772, "remote_host": "164.132.43.137", "remote_port": 5201}], "version": "iperf 3.1.3", "system_info": "Linux zeus 4.15.0-36-generic #39-Ubuntu SMP Mon Sep 24 16:19:09 UTC 2018 x86_64", "timestamp": {"time": "Thu, 18 Oct 2018 15:17:31 GMT", "timesecs": 1539875851}, "connecting_to": {"host": "164.132.43.137", "port": 5201}, "cookie": "zeus.1539875851.616014.2f4d214a1dc42", "tcp_mss_default": 1448, "test_start": {"protocol": "TCP", "num_streams": 4, "blksize": 2048, "omit": 0, "duration": 20, "bytes": 0, "blocks": 0, "reverse": 0}}, "intervals": [{"streams": [{"socket": 8, "start": 0, "end": 1.000187, "seconds": 1.000187, "bytes": 4874240, "bits_per_second": 38986623.318762, "retransmits": 22, "snd_cwnd": 241816, "rtt": 65562, "omitted": false}, {"socket": 10, "start": 0, "end": 1.000197, "seconds": 1.000197, "bytes": 3588096, "bits_per_second": 28699109.334481, "retransmits": 0, "snd_cwnd": 234576, "rtt": 65322, "omitted": false}, {"socket": 12, "start": 0, "end": 1.0002, "seconds": 1.0002, "bytes": 3128896, "bits_per_second": 25026161.937048, "retransmits": 1, "snd_cwnd": 137560, "rtt": 65208, "omitted": false}, {"socket": 14, "start": 0, "end": 1.000202, "seconds": 1.000202, "bytes": 4874240, "bits_per_second": 38986037.843606, "retransmits": 7, "snd_cwnd": 237472, "rtt": 65265, "omitted": false}], "sum": {"start": 0, "end": 1.000187, "seconds": 1.000187, "bytes": 16465472, "bits_per_second": 131699127.377728, "retransmits": 30, "omitted": false}}, {"streams": [{"socket": 8, "start": 1.000187, "end": 2.000332, "seconds": 1.000145, "bytes": 3584000, "bits_per_second": 28667844.352396, "retransmits": 3, "snd_cwnd": 192584, "rtt": 60067, "omitted": false}, {"socket": 10, "start": 1.000197, "end": 2.00034, "seconds": 1.000143, "bytes": 3584000, "bits_per_second": 28667905.858133, "retransmits": 5, "snd_cwnd": 230232, "rtt": 60543, "omitted": false}, {"socket": 12, "start": 1.0002, "end": 2.000342, "seconds": 1.000142, "bytes": 2297856, "bits_per_second": 18380236.214878, "retransmits": 0, "snd_cwnd": 160728, "rtt": 59793, "omitted": false}, {"socket": 14, "start": 1.000202, "end": 2.000344, "seconds": 1.000142, "bytes": 3584000, "bits_per_second": 28667933.194101, "retransmits": 6, "snd_cwnd": 189688, "rtt": 60140, "omitted": false}], "sum": {"start": 1.000187, "end": 2.000332, "seconds": 1.000145, "bytes": 13049856, "bits_per_second": 104383716.693411, "retransmits": 14, "omitted": false}}, {"streams": [{"socket": 8, "start": 2.000332, "end": 3.000283, "seconds": 0.999951, "bytes": 2979840, "bits_per_second": 23839890.877819, "retransmits": 3, "snd_cwnd": 149144, "rtt": 56470, "omitted": false}, {"socket": 10, "start": 2.00034, "end": 3.000291, "seconds": 0.999951, "bytes": 3399680, "bits_per_second": 27198769.361849, "retransmits": 9, "snd_cwnd": 181000, "rtt": 56858, "omitted": false}, {"socket": 12, "start": 2.000342, "end": 3.000293, "seconds": 0.999951, "bytes": 2353152, "bits_per_second": 18826140.63135, "retransmits": 2, "snd_cwnd": 123080, "rtt": 56842, "omitted": false}, {"socket": 14, "start": 2.000344, "end": 3.000296, "seconds": 0.999952, "bytes": 2834432, "bits_per_second": 22676542.708327, "retransmits": 4, "snd_cwnd": 144800, "rtt": 56695, "omitted": false}], "sum": {"start": 2.000332, "end": 3.000283, "seconds": 0.999951, "bytes": 11567104, "bits_per_second": 92541377.098229, "retransmits": 18, "omitted": false}}, {"streams": [{"socket": 8, "start": 3.000283, "end": 4.000292, "seconds": 1.000009, "bytes": 2437120, "bits_per_second": 19496783.360975, "retransmits": 0, "snd_cwnd": 165072, "rtt": 66086, "omitted": false}, {"socket": 10, "start": 3.000291, "end": 4.0003, "seconds": 1.000009, "bytes": 2990080, "bits_per_second": 23920423.283213, "retransmits": 0, "snd_cwnd": 201272, "rtt": 66053, "omitted": false}, {"socket": 12, "start": 3.000293, "end": 4.000303, "seconds": 1.00001, "bytes": 2033664, "bits_per_second": 16269149.087569, "retransmits": 0, "snd_cwnd": 137560, "rtt": 66328, "omitted": false}, {"socket": 14, "start": 3.000296, "end": 4.000305, "seconds": 1.000009, "bytes": 2373632, "bits_per_second": 18988883.962496, "retransmits": 0, "snd_cwnd": 160728, "rtt": 66446, "omitted": false}], "sum": {"start": 3.000283, "end": 4.000292, "seconds": 1.000009, "bytes": 9834496, "bits_per_second": 78675255.209583, "retransmits": 0, "omitted": false}}, {"streams": [{"socket": 8, "start": 4.000292, "end": 5.000311, "seconds": 1.000019, "bytes": 2304000, "bits_per_second": 18431648.444205, "retransmits": 0, "snd_cwnd": 170864, "rtt": 71457, "omitted": false}, {"socket": 10, "start": 4.0003, "end": 5.000319, "seconds": 1.000019, "bytes": 2867200, "bits_per_second": 22937167.976887, "retransmits": 0, "snd_cwnd": 209960, "rtt": 71501, "omitted": false}, {"socket": 12, "start": 4.000303, "end": 5.000321, "seconds": 1.000018, "bytes": 1914880, "bits_per_second": 15318762.426905, "retransmits": 0, "snd_cwnd": 143352, "rtt": 71791, "omitted": false}, {"socket": 14, "start": 4.000305, "end": 5.000323, "seconds": 1.000018, "bytes": 2244608, "bits_per_second": 17956542.911991, "retransmits": 0, "snd_cwnd": 167968, "rtt": 73739, "omitted": false}], "sum": {"start": 4.000292, "end": 5.000311, "seconds": 1.000019, "bytes": 9330688, "bits_per_second": 74644080.277155, "retransmits": 0, "omitted": false}}, {"streams": [{"socket": 8, "start": 5.000311, "end": 6.00029, "seconds": 0.999979, "bytes": 2258944, "bits_per_second": 18071931.164205, "retransmits": 0, "snd_cwnd": 179552, "rtt": 70440, "omitted": false}, {"socket": 10, "start": 5.000319, "end": 6.000298, "seconds": 0.999979, "bytes": 2334720, "bits_per_second": 18678151.883222, "retransmits": 1, "snd_cwnd": 165072, "rtt": 69975, "omitted": false}, {"socket": 12, "start": 5.000321, "end": 6.0003, "seconds": 0.999979, "bytes": 1628160, "bits_per_second": 13025553.286984, "retransmits": 1, "snd_cwnd": 121632, "rtt": 70205, "omitted": false}, {"socket": 14, "start": 5.000323, "end": 6.000303, "seconds": 0.99998, "bytes": 2269184, "bits_per_second": 18153835.569781, "retransmits": 0, "snd_cwnd": 176656, "rtt": 69952, "omitted": false}], "sum": {"start": 5.000311, "end": 6.00029, "seconds": 0.999979, "bytes": 8491008, "bits_per_second": 67929489.217402, "retransmits": 2, "omitted": false}}, {"streams": [{"socket": 8, "start": 6.00029, "end": 7.00031, "seconds": 1.00002, "bytes": 2211840, "bits_per_second": 17694365.632097, "retransmits": 0, "snd_cwnd": 191136, "rtt": 70573, "omitted": false}, {"socket": 10, "start": 6.000298, "end": 7.000329, "seconds": 1.000031, "bytes": 2211840, "bits_per_second": 17694171.579498, "retransmits": 2, "snd_cwnd": 130320, "rtt": 71093, "omitted": false}, {"socket": 12, "start": 6.0003, "end": 7.000332, "seconds": 1.000032, "bytes": 1400832, "bits_per_second": 11206297.980188, "retransmits": 1, "snd_cwnd": 97016, "rtt": 71243, "omitted": false}, {"socket": 14, "start": 6.000303, "end": 7.000334, "seconds": 1.000031, "bytes": 2211840, "bits_per_second": 17694171.579498, "retransmits": 0, "snd_cwnd": 186792, "rtt": 70683, "omitted": false}], "sum": {"start": 6.00029, "end": 7.00031, "seconds": 1.00002, "bytes": 8036352, "bits_per_second": 64289528.463286, "retransmits": 3, "omitted": false}}, {"streams": [{"socket": 8, "start": 7.00031, "end": 8.000262, "seconds": 0.999952, "bytes": 2580480, "bits_per_second": 20644834.266634, "retransmits": 1, "snd_cwnd": 157832, "rtt": 71280, "omitted": false}, {"socket": 10, "start": 7.000329, "end": 8.000268, "seconds": 0.999939, "bytes": 1640448, "bits_per_second": 13124385.048892, "retransmits": 2, "snd_cwnd": 102808, "rtt": 71276, "omitted": false}, {"socket": 12, "start": 7.000332, "end": 8.00027, "seconds": 0.999938, "bytes": 1427456, "bits_per_second": 11420355.934509, "retransmits": 0, "snd_cwnd": 104256, "rtt": 71418, "omitted": false}, {"socket": 14, "start": 7.000334, "end": 8.000271, "seconds": 0.999937, "bytes": 2580480, "bits_per_second": 20645139.456791, "retransmits": 0, "snd_cwnd": 198376, "rtt": 71460, "omitted": false}], "sum": {"start": 7.00031, "end": 8.000262, "seconds": 0.999952, "bytes": 8228864, "bits_per_second": 65834082.605823, "retransmits": 3, "omitted": false}}, {"streams": [{"socket": 8, "start": 8.000262, "end": 9.000306, "seconds": 1.000044, "bytes": 1959936, "bits_per_second": 15678796.448471, "retransmits": 3, "snd_cwnd": 125976, "rtt": 70485, "omitted": false}, {"socket": 10, "start": 8.000268, "end": 9.000314, "seconds": 1.000046, "bytes": 1531904, "bits_per_second": 12254668.104073, "retransmits": 0, "snd_cwnd": 110048, "rtt": 69390, "omitted": false}, {"socket": 12, "start": 8.00027, "end": 9.000316, "seconds": 1.000046, "bytes": 1566720, "bits_per_second": 12533183.288256, "retransmits": 0, "snd_cwnd": 115840, "rtt": 71359, "omitted": false}, {"socket": 14, "start": 8.000271, "end": 9.000318, "seconds": 1.000047, "bytes": 2293760, "bits_per_second": 18349218.165479, "retransmits": 1, "snd_cwnd": 165072, "rtt": 69151, "omitted": false}], "sum": {"start": 8.000262, "end": 9.000306, "seconds": 1.000044, "bytes": 7352320, "bits_per_second": 58815965.778487, "retransmits": 4, "omitted": false}}, {"streams": [{"socket": 8, "start": 9.000306, "end": 10.00029, "seconds": 0.999984, "bytes": 1777664, "bits_per_second": 14221539.175504, "retransmits": 0, "snd_cwnd": 134664, "rtt": 70342, "omitted": false}, {"socket": 10, "start": 9.000314, "end": 10.000298, "seconds": 0.999984, "bytes": 1607680, "bits_per_second": 12861645.452501, "retransmits": 0, "snd_cwnd": 121632, "rtt": 70477, "omitted": false}, {"socket": 12, "start": 9.000316, "end": 10.000301, "seconds": 0.999985, "bytes": 1636352, "bits_per_second": 13091012.63186, "retransmits": 0, "snd_cwnd": 127424, "rtt": 70485, "omitted": false}, {"socket": 14, "start": 9.000318, "end": 10.000303, "seconds": 0.999985, "bytes": 1986560, "bits_per_second": 15892718.714523, "retransmits": 1, "snd_cwnd": 131768, "rtt": 70918, "omitted": false}], "sum": {"start": 9.000306, "end": 10.00029, "seconds": 0.999984, "bytes": 7008256, "bits_per_second": 56066943.615869, "retransmits": 1, "omitted": false}}, {"streams": [{"socket": 8, "start": 10.00029, "end": 11.000314, "seconds": 1.000024, "bytes": 1536000, "bits_per_second": 12287707.038235, "retransmits": 1, "snd_cwnd": 104256, "rtt": 67067, "omitted": false}, {"socket": 10, "start": 10.000298, "end": 11.000323, "seconds": 1.000025, "bytes": 1574912, "bits_per_second": 12598980.59774, "retransmits": 0, "snd_cwnd": 133216, "rtt": 66789, "omitted": false}, {"socket": 12, "start": 10.000301, "end": 11.000325, "seconds": 1.000024, "bytes": 1597440, "bits_per_second": 12779212.273035, "retransmits": 0, "snd_cwnd": 139008, "rtt": 66960, "omitted": false}, {"socket": 14, "start": 10.000303, "end": 11.000327, "seconds": 1.000024, "bytes": 1597440, "bits_per_second": 12779212.273035, "retransmits": 1, "snd_cwnd": 105704, "rtt": 66762, "omitted": false}], "sum": {"start": 10.00029, "end": 11.000314, "seconds": 1.000024, "bytes": 6305792, "bits_per_second": 50445133.2943, "retransmits": 2, "omitted": false}}, {"streams": [{"socket": 8, "start": 11.000314, "end": 12.000294, "seconds": 0.99998, "bytes": 1517568, "bits_per_second": 12140784.250848, "retransmits": 1, "snd_cwnd": 81088, "rtt": 59310, "omitted": false}, {"socket": 10, "start": 11.000323, "end": 12.000302, "seconds": 0.999979, "bytes": 1904640, "bits_per_second": 15237439.694207, "retransmits": 1, "snd_cwnd": 104256, "rtt": 59075, "omitted": false}, {"socket": 12, "start": 11.000325, "end": 12.000305, "seconds": 0.99998, "bytes": 1904640, "bits_per_second": 15237425.162362, "retransmits": 2, "snd_cwnd": 107152, "rtt": 59550, "omitted": false}, {"socket": 14, "start": 11.000327, "end": 12.000307, "seconds": 0.99998, "bytes": 1904640, "bits_per_second": 15237425.162362, "retransmits": 0, "snd_cwnd": 112944, "rtt": 59215, "omitted": false}], "sum": {"start": 11.000314, "end": 12.000294, "seconds": 0.99998, "bytes": 7231488, "bits_per_second": 57853048.839061, "retransmits": 4, "omitted": false}}, {"streams": [{"socket": 8, "start": 12.000294, "end": 13.000241, "seconds": 0.999947, "bytes": 1261568, "bits_per_second": 10093080.622281, "retransmits": 0, "snd_cwnd": 91224, "rtt": 69073, "omitted": false}, {"socket": 10, "start": 12.000302, "end": 13.000248, "seconds": 0.999946, "bytes": 1740800, "bits_per_second": 13927150.43106, "retransmits": 0, "snd_cwnd": 125976, "rtt": 69882, "omitted": false}, {"socket": 12, "start": 12.000305, "end": 13.000251, "seconds": 0.999946, "bytes": 1740800, "bits_per_second": 13927153.751731, "retransmits": 0, "snd_cwnd": 130320, "rtt": 69282, "omitted": false}, {"socket": 14, "start": 12.000307, "end": 13.000252, "seconds": 0.999945, "bytes": 1740800, "bits_per_second": 13927167.034432, "retransmits": 0, "snd_cwnd": 124528, "rtt": 69462, "omitted": false}], "sum": {"start": 12.000294, "end": 13.000241, "seconds": 0.999947, "bytes": 6483968, "bits_per_second": 51874502.02945, "retransmits": 0, "omitted": false}}, {"streams": [{"socket": 8, "start": 13.000241, "end": 14.000334, "seconds": 1.000093, "bytes": 1314816, "bits_per_second": 10517550.044059, "retransmits": 0, "snd_cwnd": 101360, "rtt": 70090, "omitted": false}, {"socket": 10, "start": 13.000248, "end": 14.000343, "seconds": 1.000095, "bytes": 1863680, "bits_per_second": 14908025.36861, "retransmits": 0, "snd_cwnd": 136112, "rtt": 70226, "omitted": false}, {"socket": 12, "start": 13.000251, "end": 14.000345, "seconds": 1.000094, "bytes": 1863680, "bits_per_second": 14908039.584676, "retransmits": 0, "snd_cwnd": 141904, "rtt": 70058, "omitted": false}, {"socket": 14, "start": 13.000252, "end": 14.000355, "seconds": 1.000103, "bytes": 1863680, "bits_per_second": 14907904.533148, "retransmits": 0, "snd_cwnd": 136112, "rtt": 69982, "omitted": false}], "sum": {"start": 13.000241, "end": 14.000334, "seconds": 1.000093, "bytes": 6905856, "bits_per_second": 55241711.446363, "retransmits": 0, "omitted": false}}, {"streams": [{"socket": 8, "start": 14.000334, "end": 15.000341, "seconds": 1.000007, "bytes": 1468416, "bits_per_second": 11747243.977163, "retransmits": 0, "snd_cwnd": 112944, "rtt": 67948, "omitted": false}, {"socket": 10, "start": 14.000343, "end": 15.00035, "seconds": 1.000007, "bytes": 1665024, "bits_per_second": 13320099.902981, "retransmits": 0, "snd_cwnd": 140456, "rtt": 68192, "omitted": false}, {"socket": 12, "start": 14.000345, "end": 15.000353, "seconds": 1.000008, "bytes": 1679360, "bits_per_second": 13434771.094633, "retransmits": 2, "snd_cwnd": 110048, "rtt": 68142, "omitted": false}, {"socket": 14, "start": 14.000355, "end": 15.000355, "seconds": 1, "bytes": 1679360, "bits_per_second": 13434880, "retransmits": 0, "snd_cwnd": 147696, "rtt": 70107, "omitted": false}], "sum": {"start": 14.000334, "end": 15.000341, "seconds": 1.000007, "bytes": 6492160, "bits_per_second": 51936908.518282, "retransmits": 2, "omitted": false}}, {"streams": [{"socket": 8, "start": 15.000341, "end": 16.000322, "seconds": 0.999981, "bytes": 1685504, "bits_per_second": 13484289.192406, "retransmits": 0, "snd_cwnd": 124528, "rtt": 64502, "omitted": false}, {"socket": 10, "start": 15.00035, "end": 16.000329, "seconds": 0.999979, "bytes": 2007040, "bits_per_second": 16056656.882068, "retransmits": 2, "snd_cwnd": 104256, "rtt": 64444, "omitted": false}, {"socket": 12, "start": 15.000353, "end": 16.000332, "seconds": 0.999979, "bytes": 1937408, "bits_per_second": 15499589.194323, "retransmits": 0, "snd_cwnd": 118736, "rtt": 64016, "omitted": false}, {"socket": 14, "start": 15.000355, "end": 16.000334, "seconds": 0.999979, "bytes": 2007040, "bits_per_second": 16056656.882068, "retransmits": 0, "snd_cwnd": 159280, "rtt": 63789, "omitted": false}], "sum": {"start": 15.000341, "end": 16.000322, "seconds": 0.999981, "bytes": 7636992, "bits_per_second": 61097101.334727, "retransmits": 2, "omitted": false}}, {"streams": [{"socket": 8, "start": 16.000322, "end": 17.000324, "seconds": 1.000002, "bytes": 1804288, "bits_per_second": 14434276.468803, "retransmits": 0, "snd_cwnd": 134664, "rtt": 71559, "omitted": false}, {"socket": 10, "start": 16.000329, "end": 17.000333, "seconds": 1.000004, "bytes": 1722368, "bits_per_second": 13778888.15257, "retransmits": 0, "snd_cwnd": 125976, "rtt": 71373, "omitted": false}, {"socket": 12, "start": 16.000332, "end": 17.000335, "seconds": 1.000003, "bytes": 1726464, "bits_per_second": 13811672.484488, "retransmits": 0, "snd_cwnd": 128872, "rtt": 71492, "omitted": false}, {"socket": 14, "start": 16.000334, "end": 17.000346, "seconds": 1.000012, "bytes": 2293760, "bits_per_second": 18349856.877713, "retransmits": 0, "snd_cwnd": 169416, "rtt": 71497, "omitted": false}], "sum": {"start": 16.000322, "end": 17.000324, "seconds": 1.000002, "bytes": 7546880, "bits_per_second": 60374924.84397, "retransmits": 0, "omitted": false}}, {"streams": [{"socket": 8, "start": 17.000324, "end": 18.000227, "seconds": 0.999903, "bytes": 1525760, "bits_per_second": 12207261.637818, "retransmits": 1, "snd_cwnd": 114392, "rtt": 71034, "omitted": false}, {"socket": 10, "start": 17.000333, "end": 18.000235, "seconds": 0.999902, "bytes": 1839104, "bits_per_second": 14714273.852225, "retransmits": 0, "snd_cwnd": 136112, "rtt": 70935, "omitted": false}, {"socket": 12, "start": 17.000335, "end": 18.000238, "seconds": 0.999903, "bytes": 1851392, "bits_per_second": 14812569.826291, "retransmits": 0, "snd_cwnd": 139008, "rtt": 71297, "omitted": false}, {"socket": 14, "start": 17.000346, "end": 18.00024, "seconds": 0.999894, "bytes": 2437120, "bits_per_second": 19499028.774177, "retransmits": 0, "snd_cwnd": 181000, "rtt": 71051, "omitted": false}], "sum": {"start": 17.000324, "end": 18.000227, "seconds": 0.999903, "bytes": 7653376, "bits_per_second": 61232935.22218, "retransmits": 1, "omitted": false}}, {"streams": [{"socket": 8, "start": 18.000227, "end": 19.000279, "seconds": 1.000052, "bytes": 1288192, "bits_per_second": 10305000.395026, "retransmits": 1, "snd_cwnd": 92672, "rtt": 71368, "omitted": false}, {"socket": 10, "start": 18.000235, "end": 19.000287, "seconds": 1.000052, "bytes": 1906688, "bits_per_second": 15252711.236517, "retransmits": 0, "snd_cwnd": 140456, "rtt": 71779, "omitted": false}, {"socket": 12, "start": 18.000238, "end": 19.00029, "seconds": 1.000052, "bytes": 1914880, "bits_per_second": 15318243.830444, "retransmits": 0, "snd_cwnd": 150592, "rtt": 71457, "omitted": false}, {"socket": 14, "start": 18.00024, "end": 19.000293, "seconds": 1.000053, "bytes": 2027520, "bits_per_second": 16219301.529813, "retransmits": 3, "snd_cwnd": 152040, "rtt": 71323, "omitted": false}], "sum": {"start": 18.000227, "end": 19.000279, "seconds": 1.000052, "bytes": 7137280, "bits_per_second": 57095272.458926, "retransmits": 4, "omitted": false}}, {"streams": [{"socket": 8, "start": 19.000279, "end": 20.000289, "seconds": 1.00001, "bytes": 1288192, "bits_per_second": 10305432.805721, "retransmits": 0, "snd_cwnd": 99912, "rtt": 72110, "omitted": false}, {"socket": 10, "start": 19.000287, "end": 20.000298, "seconds": 1.000011, "bytes": 1574912, "bits_per_second": 12599157.821828, "retransmits": 2, "snd_cwnd": 117288, "rtt": 71847, "omitted": false}, {"socket": 12, "start": 19.00029, "end": 20.0003, "seconds": 1.00001, "bytes": 1925120, "bits_per_second": 15400805.782794, "retransmits": 0, "snd_cwnd": 162176, "rtt": 72005, "omitted": false}, {"socket": 14, "start": 19.000293, "end": 20.000309, "seconds": 1.000016, "bytes": 1925120, "bits_per_second": 15400713.988305, "retransmits": 1, "snd_cwnd": 121632, "rtt": 71856, "omitted": false}], "sum": {"start": 19.000279, "end": 20.000289, "seconds": 1.00001, "bytes": 6713344, "bits_per_second": 53706214.20851, "retransmits": 3, "omitted": false}}], "end": {"streams": [{"sender": {"socket": 8, "start": 0, "end": 20.000289, "seconds": 20.000289, "bytes": 41658368, "bits_per_second": 16663106.250037, "retransmits": 36, "max_snd_cwnd": 241816, "max_rtt": 72110, "min_rtt": 56470, "mean_rtt": 67841}, "receiver": {"socket": 8, "start": 0, "end": 20.000289, "seconds": 20.000289, "bytes": 39946528, "bits_per_second": 15978380.151236}}, {"sender": {"socket": 10, "start": 0, "end": 20.000289, "seconds": 20.000289, "bytes": 43554816, "bits_per_second": 17421674.481074, "retransmits": 24, "max_snd_cwnd": 234576, "max_rtt": 71847, "min_rtt": 56858, "mean_rtt": 67851}, "receiver": {"socket": 10, "start": 0, "end": 20.000289, "seconds": 20.000289, "bytes": 41943080, "bits_per_second": 16776989.403277}}, {"sender": {"socket": 12, "start": 0, "end": 20.000289, "seconds": 20.000289, "bytes": 37529152, "bits_per_second": 15011443.73322, "retransmits": 9, "max_snd_cwnd": 162176, "max_rtt": 72005, "min_rtt": 56842, "mean_rtt": 67946}, "receiver": {"socket": 12, "start": 0, "end": 20.000289, "seconds": 20.000289, "bytes": 36933720, "bits_per_second": 14773274.37717}}, {"sender": {"socket": 14, "start": 0, "end": 20.000289, "seconds": 20.000289, "bytes": 46729216, "bits_per_second": 18691416.1205, "retransmits": 24, "max_snd_cwnd": 237472, "max_rtt": 73739, "min_rtt": 56695, "mean_rtt": 67974}, "receiver": {"socket": 14, "start": 0, "end": 20.000289, "seconds": 20.000289, "bytes": 45373088, "bits_per_second": 18148972.764278}}], "sum_sent": {"start": 0, "end": 20.000289, "seconds": 20.000289, "bytes": 169471552, "bits_per_second": 67787640.584832, "retransmits": 93}, "sum_received": {"start": 0, "end": 20.000289, "seconds": 20.000289, "bytes": 164196416, "bits_per_second": 65677616.69596}, "cpu_utilization_percent": {"host_total": 2.335499, "host_user": 0.345061, "host_system": 1.990452, "remote_total": 2.22908, "remote_user": 0.309963, "remote_system": 1.91882}}}